jhu/__init__.py
jhu/auth.py
jhu/email.py
jhu/orm.py
jhu/security.py
jhu/webhook.py
jhu-1.7.4.dist-info/licenses/LICENSE
jhu-1.7.4.dist-info/METADATA
jhu-1.7.4.dist-info/WHEEL
jhu-1.7.4.dist-info/top_level.txt
jhu-1.7.4.dist-info/zip-safe
jhu-1.7.4.dist-info/RECORD
